dax_sql_parser/__init__.py
dax_sql_parser/core/__init__.py
dax_sql_parser/core/ast.py
dax_sql_parser/core/dialects/__init__.py
dax_sql_parser/core/dialects/base.py
dax_sql_parser/core/dialects/common.py
dax_sql_parser/core/dialects/registry.py
dax_sql_parser/core/dialects/trino.py
dax_sql_parser/core/engine.py
dax_sql_parser/core/exceptions.py
dax_sql_parser/core/metadata.py
dax_sql_parser/core/parser.py
dax_sql_parser/core/translator.py
dax_sql_parser/grammar/Dax.g4
dax_sql_parser/grammar/Dax.interp
dax_sql_parser/grammar/Dax.tokens
dax_sql_parser/grammar/DaxLexer.interp
dax_sql_parser/grammar/DaxLexer.py
dax_sql_parser/grammar/DaxLexer.tokens
dax_sql_parser/grammar/DaxParser.py
dax_sql_parser/grammar/DaxVisitor.py
dax_sql_parser/grammar/__init__.py
dax_sql_parser/py.typed
dax_sql_parser-0.1.0.dist-info/WHEEL
dax_sql_parser-0.1.0.dist-info/METADATA
dax_sql_parser-0.1.0.dist-info/RECORD
