Metadata-Version: 2.3
Name: dax-sql-parser
Version: 0.1.0
Summary: A powerful DAX to SQL parser and translator with multi-dialect support.
Author: Shoham Yamin
Author-email: Shoham Yamin <shoham39@gmail.com>
Requires-Dist: antlr4-python3-runtime>=4.13.2
Requires-Dist: sqlglot>=28.5.0
Requires-Python: >=3.12
